MANIFEST.in
README.md
setup.cfg
setup.py
bin/heroin
heroin/__init__.py
heroin/test.py
heroin/trial.py
heroin.egg-info/PKG-INFO
heroin.egg-info/SOURCES.txt
heroin.egg-info/dependency_links.txt
heroin.egg-info/requires.txt
heroin.egg-info/top_level.txt