Metadata-Version: 1.1
Name: heroin
Version: 0.0.2
Summary: `heroin`.
Home-page: https://github.com/anthonyalmarza/heroin
Author: Anthony
Author-email: UNKNOWN
License: UNKNOWN
Keywords: heroin
Platform: UNKNOWN
Classifier: Intended Audience :: Developers
Classifier: Natural Language :: English
Classifier: Operating System :: OS Independent
Classifier: Programming Language :: Python
